{
  "noiseKey": {
    "private": {
      "type": "Buffer",
      "data": "6Kq+SLPnDAv7il6C3SCe/10Mgw9dj6NV3Cbe611x+kc="
    },
    "public": {
      "type": "Buffer",
      "data": "uoW5syQo67ywexTN/vyQNBPD32toTqb4wL7rg+wcMx0="
    }
  },
  "pairingEphemeralKeyPair": {
    "private": {
      "type": "Buffer",
      "data": "uFdPqqaiVboan9Egi0rnH9SfT8q33USlIOCCpUbEmEY="
    },
    "public": {
      "type": "Buffer",
      "data": "h5OjJm+wg1n7XDamku1NS8GRT9tTAXdyw6LALhCo9QY="
    }
  },
  "signedIdentityKey": {
    "private": {
      "type": "Buffer",
      "data": "+HIvT6tlQJVte/MCtCZQu5I7T+JkcWZmB/ceaC/Aels="
    },
    "public": {
      "type": "Buffer",
      "data": "cLt+dPq7TjodYgALfI4KeAAGOUt3E0Ndm2kWyzCtKkk="
    }
  },
  "signedPreKey": {
    "keyPair": {
      "private": {
        "type": "Buffer",
        "data": "0Hgh+PgV5H5xtTk4IlWD07sIQjdycyj6etHZzASItG0="
      },
      "public": {
        "type": "Buffer",
        "data": "VriTe7Vkr+Qr0YCyxuTvsEF1IejBQPVywnviFg6tok0="
      }
    },
    "signature": {
      "type": "Buffer",
      "data": "4nAuJZgus7dCXwWo8yym0HBJMZ6+hEnrhIUUhPXPRQnvP8wCBkYdgUjHcHShRLH4xwsbD+na/XBPGTDlvYS9gg=="
    },
    "keyId": 1
  },
  "registrationId": 203,
  "advSecretKey": "731Th+rdLcSTO68Mcs5vo4Nyjj8tI+FikK6YLgltZ+Y=",
  "processedHistoryMessages": [
    {
      "key": {
        "remoteJid": "94717132823@s.whatsapp.net",
        "fromMe": true,
        "id": "0BEE5A3346A45353776E6A5AA19735DA"
      },
      "messageTimestamp": 1749424152
    },
    {
      "key": {
        "remoteJid": "94717132823@s.whatsapp.net",
        "fromMe": true,
        "id": "D97C9C136FA2F1DEEC60ADB0ED20FC0A"
      },
      "messageTimestamp": 1749424205
    },
    {
      "key": {
        "remoteJid": "94717132823@s.whatsapp.net",
        "fromMe": true,
        "id": "166BC9CCADA17247F55984F178AC4DDD"
      },
      "messageTimestamp": 1749424424
    },
    {
      "key": {
        "remoteJid": "94717132823@s.whatsapp.net",
        "fromMe": true,
        "id": "99075EFCF349BE06107AA656B848510F"
      },
      "messageTimestamp": 1749424519
    },
    {
      "key": {
        "remoteJid": "94717132823@s.whatsapp.net",
        "fromMe": true,
        "id": "24145CC2448B604800DA6D4F3EF40ED1"
      },
      "messageTimestamp": 1749424585
    },
    {
      "key": {
        "remoteJid": "94717132823@s.whatsapp.net",
        "fromMe": true,
        "id": "7A0A4D756BECA00D4294F5F03359A25B"
      },
      "messageTimestamp": 1749424645
    },
    {
      "key": {
        "remoteJid": "94717132823@s.whatsapp.net",
        "fromMe": true,
        "id": "552A1B97F87BFF58DB2A49B171D99B4A"
      },
      "messageTimestamp": 1749424695
    },
    {
      "key": {
        "remoteJid": "94717132823@s.whatsapp.net",
        "fromMe": true,
        "id": "28D3B88F1C4437B4C704714C87A0B427"
      },
      "messageTimestamp": 1749424735
    },
    {
      "key": {
        "remoteJid": "94717132823@s.whatsapp.net",
        "fromMe": true,
        "id": "DBB7C32A5305AEF6D1611265019118E0"
      },
      "messageTimestamp": 1749424771
    },
    {
      "key": {
        "remoteJid": "94717132823@s.whatsapp.net",
        "fromMe": true,
        "id": "A4CD5BD975308D022547E73D5FAE6017"
      },
      "messageTimestamp": 1749424805
    },
    {
      "key": {
        "remoteJid": "94717132823@s.whatsapp.net",
        "fromMe": true,
        "id": "981F236B2F18900EFDAEFAB005A242FC"
      },
      "messageTimestamp": 1749424824
    }
  ],
  "nextPreKeyId": 74,
  "firstUnuploadedPreKeyId": 74,
  "accountSyncCounter": 1,
  "accountSettings": {
    "unarchiveChats": false
  },
  "deviceI